_tomographer_cxx
tomographer
