Metadata-Version: 1.1
Name: tomographer
Version: 5.4
Summary: The Tomographer Project — Practical, Reliable Error Bars in Quantum Tomography
Home-page: https://github.com/Tomographer/tomographer/
Author: Philippe Faist
Author-email: phfaist@caltech.edu
License: MIT
Download-URL: https://github.com/Tomographer/tomographer/releases/download/v5.4/tomographer-v5.4.tar.gz
Keywords: quantum tomography error bars
Platform: UNKNOWN
Classifier: Development Status :: 5 - Production/Stable
Classifier: Intended Audience :: Science/Research
Classifier: License :: OSI Approved :: MIT License
Classifier: Programming Language :: C++
Classifier: Programming Language :: Python
Classifier: Topic :: Scientific/Engineering :: Physics
